{
    "data": {
        "searchInboxes": [
            {
                "id": "cl0h7p9g500100wl7bhc40mgy",
                "imageUrl": "https://i.discogs.com/zCWg17jk4eNVS7WV_iPO2xT2zHfAQFV0wmjsyrcaHkA/rs:fit/g:sm/q:90/h:500/w:500/czM6Ly9kaXNjb2dz/LWRhdGFiYXNlLWlt/YWdlcy9MLTc5Nzcz/MS0xNDM1NTg4MTg2/LTMzNzkuanBlZw.jpeg",
                "imageKey": "images/smtw9sygahonzknemi816.png",
                "name": "CUFF",
                "slug": "thisiscuff",
                "type": "LABEL",
                "averageReviewTime": 8
            },
            {
                "id": "ckybdbkf800100wmpq1p31ed4",
                "imageUrl": "https://res.cloudinary.com/trackstack/image/upload/v1641981552/Issues_Logo_mdnggo.jpg",
                "imageKey": null,
                "name": "ISSUES",
                "slug": "issues",
                "type": "LABEL",
                "averageReviewTime": 9
            },
            {
                "id": "cl2stjbn9005509jyu424pmti",
                "imageUrl": "",
                "imageKey": "images/vcf4drtlphl1kibgzjzqr.png",
                "name": "REALM Records",
                "slug": "realmrecords",
                "type": "LABEL",
                "averageReviewTime": 77
            },
            {
                "id": "cky46d2x700720wl8mvmb6hbo",
                "imageUrl": "https://res.cloudinary.com/trackstack/image/upload/v1641548877/b99061cb-7f10-4b0e-81e4-47fc217db310_kkki86.jpg",
                "imageKey": "images/4nftfhg6qe_cngjugwmen.png",
                "name": "Wheats",
                "slug": "wheats",
                "type": "LABEL",
                "averageReviewTime": 42
            },
            {
                "id": "cl81d8wei002109mg4jhmlkjb",
                "imageUrl": "https://res.cloudinary.com/trackstack/image/upload/v1663144558/WhatsApp_Image_2022-09-14_at_9.13.26_AM_e2aelg.jpg",
                "imageKey": "images%2FThoydZBg5gT__QIFTNpoM%2Flibero%202023%20logo%20bg%20copy%202.jpg",
                "name": "Libero Records",
                "slug": "libero-records",
                "type": "LABEL",
                "averageReviewTime": 14
            },
            {
                "id": "ckw0ihzys00442cxyukuvoux4",
                "imageUrl": "https://res.cloudinary.com/trackstack/image/upload/v1636971541/sura_music_d4vqgy.jpg",
                "imageKey": null,
                "name": "SURA Music",
                "slug": "suramusic",
                "type": "LABEL",
                "averageReviewTime": 10
            },
            {
                "id": "cla8bg954000cmn0mcy58ov4s",
                "imageUrl": "https://res.cloudinary.com/trackstack/image/upload/v1667918270/avatars-000261492022-uz7tpc-t500x500_cjx0rl.jpg",
                "imageKey": null,
                "name": "VIVa MUSiC Label Group",
                "slug": "viva-music-label-group-demos",
                "type": "LABEL",
                "averageReviewTime": 14
            },
            {
                "id": "cktokgzoy13040wle958xyuts",
                "imageUrl": "https://res.cloudinary.com/trackstack/image/upload/v1639912828/avatars-bMpxUz0T6imIQUgQ-1MY7zg-t500x500_en8fyy.jpg",
                "imageKey": null,
                "name": "Reecords",
                "slug": "reecords",
                "type": "LABEL",
                "averageReviewTime": 22
            },
            {
                "id": "ckxa7j4pv00350wjx693xevec",
                "imageUrl": "https://i1.sndcdn.com/avatars-7QSRxNw47cyRWGa2-oeIMNg-t500x500.jpg",
                "imageKey": null,
                "name": "Niteplan",
                "slug": "niteplan",
                "type": "LABEL",
                "averageReviewTime": 7
            },
            {
                "id": "clc90s1sl04950jjxenq6xs6b",
                "imageUrl": "https://res.cloudinary.com/trackstack/image/upload/v1672314449/ZHgT5yt0_hywv2b.jpg",
                "imageKey": null,
                "name": "Cuttin Headz",
                "slug": "cuttinheadz",
                "type": "LABEL",
                "averageReviewTime": 35
            },
            {
                "id": "clcvyaffg00390kmi1svsnxyz",
                "imageUrl": "https://res.cloudinary.com/trackstack/image/upload/v1673700811/TBX_LOGO_1440_jbqmdc.jpg",
                "imageKey": null,
                "name": "TBX Records",
                "slug": "tbxrecords",
                "type": "LABEL",
                "averageReviewTime": 11
            },
            {
                "id": "cle5u9h0002000kjvcq22az7k",
                "imageUrl": "https://res.cloudinary.com/trackstack/image/upload/v1676475551/sos_yfypav.jpg",
                "imageKey": null,
                "name": "Sink or Swim",
                "slug": "sinkorswim",
                "type": "LABEL",
                "averageReviewTime": 10
            },
            {
                "id": "cld0tsqkk00210mmkoe53sl7p",
                "imageUrl": "https://res.cloudinary.com/trackstack/image/upload/v1673996087/9_dwojry.jpg",
                "imageKey": null,
                "name": "CID [Night Service Only]",
                "slug": "cid-night-service-only",
                "type": "LABEL",
                "averageReviewTime": 12
            },
            {
                "id": "clewyiat603200kmoc1s5nbg7",
                "imageUrl": "https://res.cloudinary.com/trackstack/image/upload/v1678115256/avatars-z10VOUZ2a2Hy4L1t-IU2MgA-t500x500_wxuzca.jpg",
                "imageKey": null,
                "name": "Techne Records",
                "slug": "technerecords",
                "type": "LABEL",
                "averageReviewTime": 24
            },
            {
                "id": "clfgwf0yr00290kldzb45t1ek",
                "imageUrl": "https://res.cloudinary.com/trackstack/image/upload/v1679135916/Moon_Harbour_m6w3yi.jpg",
                "imageKey": null,
                "name": "Moon Harbour",
                "slug": "moonharbour",
                "type": "LABEL",
                "averageReviewTime": 7
            },
            {
                "id": "cldedzh1l00260kjrj7tmzwjh",
                "imageUrl": "https://res.cloudinary.com/trackstack/image/upload/v1674815651/download_m0u9xk.png",
                "imageKey": null,
                "name": "Roush",
                "slug": "roush",
                "type": "LABEL",
                "averageReviewTime": 7
            },
            {
                "id": "clfjvc7a000940lmomcncfp03",
                "imageUrl": null,
                "imageKey": "images/0jouyoivrqfdnmuo9bunq.png",
                "name": "Mindshake Records",
                "slug": "mindshakerecords",
                "type": "LABEL",
                "averageReviewTime": 7
            },
            {
                "id": "cl5uqi63r017009l7y12s3lqa",
                "imageUrl": "https://d1fdloi71mui9q.cloudfront.net/y25i20sUQoGTiuu1dtyr_3fL43iQuycM3fOll",
                "imageKey": null,
                "name": "Encasa Records",
                "slug": "encasarecords",
                "type": "LABEL",
                "averageReviewTime": 29
            },
            {
                "id": "cldmzkz7x00590mjh4p7uxk7m",
                "imageUrl": "https://res.cloudinary.com/trackstack/image/upload/v1675335628/Screenshot_2023-02-02_at_10.59.03_gfepnh.png",
                "imageKey": null,
                "name": "Techaway Records",
                "slug": "techawayrecords",
                "type": "LABEL",
                "averageReviewTime": 14
            },
            {
                "id": "clekg7nr900590jl93pzc33wx",
                "imageUrl": null,
                "imageKey": "images/s5fqto7sufv3fiiukpmdg.png",
                "name": "Hood Politics Records",
                "slug": "hoodpoliticsrecords",
                "type": "LABEL",
                "averageReviewTime": 7
            },
            {
                "id": "ckz5w1tmv00410wmgqsat5gy0",
                "imageUrl": "https://res.cloudinary.com/trackstack/image/upload/v1672424546/oX16HjIA_vvzb2z.jpg",
                "imageKey": null,
                "name": "Zealous Records",
                "slug": "zealous",
                "type": "LABEL",
                "averageReviewTime": 37
            },
            {
                "id": "cl6hthrw4001009i3bczsiwuj",
                "imageUrl": "https://res.cloudinary.com/trackstack/image/upload/v1659785726/254901505_580202803230541_3369576845306521875_n_zwce8c.jpg",
                "imageKey": "images/e7unrq1tzbvafbxnjmh_f.png",
                "name": "Retail Records",
                "slug": "retailrecords",
                "type": "LABEL",
                "averageReviewTime": 7
            },
            {
                "id": "clakuuj9100210nlbfztqp51r",
                "imageUrl": "https://res.cloudinary.com/trackstack/image/upload/v1669665776/122729364_185443993050803_4771807746722913232_n_psj4nf.jpg",
                "imageKey": null,
                "name": "Boogeyman",
                "slug": "boogeyman",
                "type": "LABEL",
                "averageReviewTime": 20
            },
            {
                "id": "cle5vt0x405170jjuuhdhr2d5",
                "imageUrl": null,
                "imageKey": "images/4ckde8v2l7qtq3jhrol4v.png",
                "name": "Andhera Records",
                "slug": "andhera",
                "type": "LABEL",
                "averageReviewTime": 7
            },
            {
                "id": "clfa5jt6k00480mjsv6zjy15r",
                "imageUrl": "",
                "imageKey": "images/kwzhzqssih1a7c-lfolya.png",
                "name": "Black Book Records",
                "slug": "blackbookrecords",
                "type": "LABEL",
                "averageReviewTime": 15
            },
            {
                "id": "cldtzxtks03650lmiymakfoko",
                "imageUrl": null,
                "imageKey": "images/jwn2nzgerx4g3lz7025ph.png",
                "name": "Black Seven Music",
                "slug": "blacksevenmusic",
                "type": "LABEL",
                "averageReviewTime": 7
            },
            {
                "id": "clbfb5osz00210njs6wodht40",
                "imageUrl": "https://res.cloudinary.com/trackstack/image/upload/v1670681037/logo_innocent_qzubbj.png",
                "imageKey": null,
                "name": "Innocent Music",
                "slug": "innocentmusic",
                "type": "LABEL",
                "averageReviewTime": 7
            },
            {
                "id": "cler1dfs903090mmolk9o7p84",
                "imageUrl": null,
                "imageKey": "images/l4kzonp91opa-babm-9wa.png",
                "name": "Hot Creations",
                "slug": "hotcreations",
                "type": "LABEL",
                "averageReviewTime": 12
            },
            {
                "id": "cld4d838q00210kmt0von3nft",
                "imageUrl": "https://res.cloudinary.com/trackstack/image/upload/v1674209937/Techords_Logo_White_xmckvb.jpg",
                "imageKey": null,
                "name": "Techords",
                "slug": "techords",
                "type": "LABEL",
                "averageReviewTime": 7
            },
            {
                "id": "cl8czn3id000109julm7di1c8",
                "imageUrl": "https://res.cloudinary.com/trackstack/image/upload/v1663842618/300002629_1264370484323040_176199814029667943_n_ivlcdh.jpg",
                "imageKey": null,
                "name": "Tamango Records",
                "slug": "tamango",
                "type": "LABEL",
                "averageReviewTime": 1
            },
            {
                "id": "cl2ny5zh500100wl4rfvqex3v",
                "imageUrl": "https://res.cloudinary.com/trackstack/image/upload/v1683131550/box_zdliys.jpg",
                "imageKey": null,
                "name": "Box of Cats",
                "slug": "box-of-cats",
                "type": "LABEL",
                "averageReviewTime": 14
            },
            {
                "id": "cl92s273t012509mv5e76ist9",
                "imageUrl": "https://res.cloudinary.com/trackstack/image/upload/v1665406472/271169875_4831050193653784_3105629375461507545_n_njid47.jpg",
                "imageKey": null,
                "name": "Koloka Records",
                "slug": "kolokarecords",
                "type": "LABEL",
                "averageReviewTime": 7
            },
            {
                "id": "clgde6t2l01280kldc68s3kcp",
                "imageUrl": null,
                "imageKey": "images/vnk3avyg3swilza9kjbou.png",
                "name": "Maccabi House Team",
                "slug": "maccabihouse",
                "type": "LABEL",
                "averageReviewTime": 7
            },
            {
                "id": "cl59dbz35000109id78azxo6u",
                "imageUrl": "https://i1.sndcdn.com/artworks-000138026096-y1ljj9-t500x500.jpg",
                "imageKey": null,
                "name": "Lost Records",
                "slug": "lostrecords",
                "type": "LABEL",
                "averageReviewTime": 12
            },
            {
                "id": "clciwpfo801310kl35wzt1g25",
                "imageUrl": null,
                "imageKey": "images/37tbwrrvw6nj5xxt2wzex.png",
                "name": "Canibales",
                "slug": "canibales",
                "type": "LABEL",
                "averageReviewTime": 7
            },
            {
                "id": "cldk8yjck00210jl7lggygnmz",
                "imageUrl": "https://res.cloudinary.com/trackstack/image/upload/v1675252943/WhatsApp_Image_2023-02-01_at_11.47.36_teac2t.jpg",
                "imageKey": "",
                "name": "hedZup records",
                "slug": "hedzuprecords",
                "type": "LABEL",
                "averageReviewTime": 13
            },
            {
                "id": "cle2kx9fl08460pjtqhjgebmj",
                "imageUrl": null,
                "imageKey": "images/s0qfwlvlvdzuw190oamqp.png",
                "name": "Seven Dials Records",
                "slug": "seven-dials-records",
                "type": "LABEL",
                "averageReviewTime": 7
            },
            {
                "id": "clckn81c200250kl8ecdarobp",
                "imageUrl": "https://res.cloudinary.com/trackstack/image/upload/v1673583327/till_ma9jxw.png",
                "imageKey": "images%2FuqsBty9m1TaPJHXc0zqZc%2Frenderedimage.jpeg",
                "name": "Till? Records",
                "slug": "tillrecords",
                "type": "LABEL",
                "averageReviewTime": 7
            },
            {
                "id": "clfu67rix02430lld7p2elmph",
                "imageUrl": "https://res.cloudinary.com/trackstack/image/upload/v1680123649/denser_cr8105.jpg",
                "imageKey": null,
                "name": "DENSER",
                "slug": "denser",
                "type": "LABEL",
                "averageReviewTime": 7
            },
            {
                "id": "clcudjgkq02180nl8htrgag40",
                "imageUrl": "https://res.cloudinary.com/trackstack/image/upload/v1673609788/Likeminded_-_Logo_Black_Transparent_600x600_hnpggf.jpg",
                "imageKey": null,
                "name": "likeminded",
                "slug": "likeminded",
                "type": "LABEL",
                "averageReviewTime": 15
            },
            {
                "id": "clchq00us00210kl7ohu0vua5",
                "imageUrl": "https://res.cloudinary.com/trackstack/image/upload/v1672840459/LOGO_LAC_2_mfc6em.png",
                "imageKey": null,
                "name": "La Confrerie",
                "slug": "laconfrerie",
                "type": "LABEL",
                "averageReviewTime": 14
            },
            {
                "id": "cler1d1xk02240mmof6q802a8",
                "imageUrl": null,
                "imageKey": "images/y1gljygxwnsk6_npbu7xh.png",
                "name": "Hottrax",
                "slug": "hottrax",
                "type": "LABEL",
                "averageReviewTime": 11
            },
            {
                "id": "cl5uqh77j015509l78kd9020v",
                "imageUrl": "https://d1fdloi71mui9q.cloudfront.net/9JpCCzyjTIAai6vMnkd3_u0EG988FtJPK36Ay",
                "imageKey": null,
                "name": "CLU RECS",
                "slug": "clurecs",
                "type": "LABEL",
                "averageReviewTime": 16
            },
            {
                "id": "clh9dnx2u00860jl1pk3uspzc",
                "imageUrl": "https://res.cloudinary.com/trackstack/image/upload/v1683219850/size_d8ikad.jpg",
                "imageKey": null,
                "name": "Size Records",
                "slug": "size",
                "type": "LABEL",
                "averageReviewTime": 7
            },
            {
                "id": "cley4vs3b02860kl06ve08m0j",
                "imageUrl": null,
                "imageKey": "images/-ycjtavqb9fkl9m2vvdf9.png",
                "name": "BINARY",
                "slug": "binary",
                "type": "LABEL",
                "averageReviewTime": 9
            },
            {
                "id": "clek7kve200430pmhnvimq2om",
                "imageUrl": "https://res.cloudinary.com/trackstack/image/upload/v1677344315/car_ycg63b.png",
                "imageKey": null,
                "name": "Catch&Release",
                "slug": "catchandrelease",
                "type": "LABEL",
                "averageReviewTime": 37
            },
            {
                "id": "clfhe4aqw00490kmfpncphvvs",
                "imageUrl": "https://res.cloudinary.com/trackstack/image/upload/v1679350768/rendr_dxliqb.jpg",
                "imageKey": null,
                "name": "Rendr. Records",
                "slug": "rendrrecords",
                "type": "LABEL",
                "averageReviewTime": 17
            },
            {
                "id": "cl8bs8djb002309iaphv1qvwi",
                "imageUrl": "https://res.cloudinary.com/trackstack/image/upload/v1663881472/KOOK_-_B_N_wiqo2y.jpg",
                "imageKey": null,
                "name": "KOOK Label",
                "slug": "kook",
                "type": "LABEL",
                "averageReviewTime": 7
            },
            {
                "id": "clgezhu9600930jl979mb2r1l",
                "imageUrl": "https://res.cloudinary.com/trackstack/image/upload/v1681382099/deeperfect_p6qrxg.jpg",
                "imageKey": null,
                "name": "DEEPERFECT",
                "slug": "deeperfect",
                "type": "LABEL",
                "averageReviewTime": 7
            },
            {
                "id": "cle5upi3500070kmh2p705kz2",
                "imageUrl": "https://res.cloudinary.com/trackstack/image/upload/v1676219759/Family_Partner_Logo_teons2.jpg",
                "imageKey": null,
                "name": "Family Partner",
                "slug": "familypartner",
                "type": "LABEL",
                "averageReviewTime": 7
            },
            {
                "id": "clciwnc7y00210kl3q44qhb2m",
                "imageUrl": "https://res.cloudinary.com/trackstack/image/upload/v1673421825/THUNDR_LOGO_WHITE_BACKGROUND_luopsu.png",
                "imageKey": null,
                "name": "THUNDR",
                "slug": "thundr",
                "type": "LABEL",
                "averageReviewTime": 8
            },
            {
                "id": "cl9rjnyhy0001mn0lvnx2jz2e",
                "imageUrl": "https://res.cloudinary.com/trackstack/image/upload/v1666899289/blackrelativefull_xvw81d.png",
                "imageKey": null,
                "name": "Relative Music",
                "slug": "relativemusic",
                "type": "LABEL",
                "averageReviewTime": 7
            },
            {
                "id": "clbnytp8200510jl3gq24jxv1",
                "imageUrl": "https://res.cloudinary.com/trackstack/image/upload/v1671041289/292110797_556691159504515_8552611548278309062_n_rae0oi.jpg",
                "imageKey": null,
                "name": "Mood Child",
                "slug": "moodchild",
                "type": "LABEL",
                "averageReviewTime": 13
            },
            {
                "id": "clbv3hiz900210lleobct5bbu",
                "imageUrl": "https://res.cloudinary.com/trackstack/image/upload/v1671472293/Screenshot_2022-12-19_at_17.50.47_lzn008.png",
                "imageKey": null,
                "name": "Samani Music",
                "slug": "samanimusic",
                "type": "LABEL",
                "averageReviewTime": 8
            },
            {
                "id": "cl9rjquz4000imn0ldznk2u8v",
                "imageUrl": "https://res.cloudinary.com/trackstack/image/upload/v1666899293/1400x1400px_Scratched_Logo_premhi.jpg",
                "imageKey": null,
                "name": "DESIGN_ Records",
                "slug": "designrecords",
                "type": "LABEL",
                "averageReviewTime": 31
            },
            {
                "id": "cle6z2q9y02700ll9gnf3a44w",
                "imageUrl": "https://res.cloudinary.com/trackstack/image/upload/v1676625870/hotl_zzxcpf.jpg",
                "imageKey": null,
                "name": "HoTL Records",
                "slug": "hotlrecords",
                "type": "LABEL",
                "averageReviewTime": 13
            },
            {
                "id": "cl5sd5hdp000509k2e0be3gqt",
                "imageUrl": "https://res.cloudinary.com/trackstack/image/upload/v1658246579/WhatsApp_Image_2022-07-19_at_5.43.56_PM_1_cnjhyo.jpg",
                "imageKey": null,
                "name": "Arritmia",
                "slug": "arritmia",
                "type": "LABEL",
                "averageReviewTime": 9
            },
            {
                "id": "clg6jyd4a02570jl4ddnxkvim",
                "imageUrl": null,
                "imageKey": "images/pudnfzn36fn4ublhkvipg.png",
                "name": "PIV Records",
                "slug": "pivrecords",
                "type": "LABEL",
                "averageReviewTime": 7
            },
            {
                "id": "cler1expc00930kjyeiwc82h2",
                "imageUrl": null,
                "imageKey": "images/j7lwnm9oqq9fd0brcsakm.png",
                "name": "Paradise Records",
                "slug": "paradiserecords",
                "type": "LABEL",
                "averageReviewTime": 12
            },
            {
                "id": "clfsp8ro000660jkzsb3z373m",
                "imageUrl": "https://res.cloudinary.com/trackstack/image/upload/v1680034532/0016217986_10_tjycsq.jpg",
                "imageKey": null,
                "name": "Psicodelica",
                "slug": "psicodelica",
                "type": "LABEL",
                "averageReviewTime": 7
            },
            {
                "id": "cldus8g5u00280kmnug7jnjhu",
                "imageUrl": "https://res.cloudinary.com/trackstack/image/upload/v1675806715/39322_l4acn1.jpg",
                "imageKey": "images/8vqk8vs9rivo07ca9wd4j.png",
                "name": "Sankeys Records",
                "slug": "sankeysrecords",
                "type": "LABEL",
                "averageReviewTime": 7
            },
            {
                "id": "clfwi2poh00220kl2an9kzdfo",
                "imageUrl": "https://res.cloudinary.com/trackstack/image/upload/v1681728119/Hell-Beach-Logo-500x500_zybpds.jpg",
                "imageKey": null,
                "name": "Hell Beach Records",
                "slug": "hellbeach",
                "type": "LABEL",
                "averageReviewTime": 1
            },
            {
                "id": "clepj5ja202360kmn4p1uqbuq",
                "imageUrl": null,
                "imageKey": "images/mb1hepm3y8dajdfoxxhej.png",
                "name": "Edible Records",
                "slug": "ediblerecords",
                "type": "LABEL",
                "averageReviewTime": 7
            },
            {
                "id": "cla8bvtrr002bmg0jhb6qrv99",
                "imageUrl": "https://res.cloudinary.com/trackstack/image/upload/v1667919237/maxresdefault_1_lk2ntj.png",
                "imageKey": null,
                "name": "Fuse",
                "slug": "fuse",
                "type": "LABEL",
                "averageReviewTime": 7
            },
            {
                "id": "clgpjk19911850kmbqzilrwgl",
                "imageUrl": "https://res.cloudinary.com/trackstack/image/upload/v1682019831/mos_rsrixz.jpg",
                "imageKey": null,
                "name": "Ministry of Sound",
                "slug": "ministryofsound",
                "type": "LABEL",
                "averageReviewTime": 7
            },
            {
                "id": "clepjaalg04330ljlm81mj43r",
                "imageUrl": null,
                "imageKey": "images/018kwm2qv1mbxnekrijgk.png",
                "name": "Heavy House Society",
                "slug": "heavyhousesociety",
                "type": "LABEL",
                "averageReviewTime": 12
            },
            {
                "id": "cldiswad900790linrnrxaskm",
                "imageUrl": "https://res.cloudinary.com/trackstack/image/upload/v1675082332/Untitled_design_5_lt19kp.png",
                "imageKey": null,
                "name": "Deeperdub Records",
                "slug": "deeperdubrecords",
                "type": "LABEL",
                "averageReviewTime": 7
            },
            {
                "id": "cld4etr7n04050klalih4en7y",
                "imageUrl": "https://res.cloudinary.com/trackstack/image/upload/v1674211520/plump_ytvqdz.png",
                "imageKey": null,
                "name": "Plump Records",
                "slug": "plumprecords",
                "type": "LABEL",
                "averageReviewTime": 8
            },
            {
                "id": "cl2xgadb3001009jmpwvw6vgr",
                "imageUrl": null,
                "imageKey": "images/ldda0cjgt1xyck-htcigd.png",
                "name": "Unknown-ID",
                "slug": "unknownid",
                "type": "LABEL",
                "averageReviewTime": 19
            },
            {
                "id": "clbam3iqt01480kletcrtpz93",
                "imageUrl": "https://res.cloudinary.com/trackstack/image/upload/v1670234310/avatars-rduVqLlLwBo6yhpa-I4c4Mg-t500x500_xdhb2l.jpg",
                "imageKey": null,
                "name": "Etiquette",
                "slug": "etiquette",
                "type": "LABEL",
                "averageReviewTime": 36
            },
            {
                "id": "clf8glrau10400kmny2zzuvhn",
                "imageUrl": "https://res.cloudinary.com/trackstack/image/upload/v1678810741/338_kdjzdq.jpg",
                "imageKey": null,
                "name": "Release LDN",
                "slug": "releaseldn",
                "type": "LABEL",
                "averageReviewTime": 8
            },
            {
                "id": "clh994s9901060kl7s1pjxmy1",
                "imageUrl": null,
                "imageKey": "images/_q5wdd2mqkvwv6rgbp6u9.png",
                "name": "GRITTY",
                "slug": "gritty",
                "type": "LABEL",
                "averageReviewTime": 7
            },
            {
                "id": "clgcfhdv700800mldukrkon3x",
                "imageUrl": "https://res.cloudinary.com/trackstack/image/upload/v1681227507/HouseHats_Records_1_1_zeehqq.jpg",
                "imageKey": null,
                "name": "House Hats Records",
                "slug": "househatsrecords",
                "type": "LABEL",
                "averageReviewTime": 7
            },
            {
                "id": "clgqnbvbr00550kjnpxyoub37",
                "imageUrl": "https://res.cloudinary.com/trackstack/image/upload/v1682087295/notforme_lncwl4.jpg",
                "imageKey": null,
                "name": "NotForMe",
                "slug": "notforme",
                "type": "LABEL",
                "averageReviewTime": 7
            },
            {
                "id": "cld4ez46x05780kla872qcoqf",
                "imageUrl": "https://res.cloudinary.com/trackstack/image/upload/v1674211513/432_lwisu8.png",
                "imageKey": null,
                "name": "FOUR THIRTY TWO",
                "slug": "fourthirtytwo",
                "type": "LABEL",
                "averageReviewTime": 7
            },
            {
                "id": "clh7up2cb06710kmnbqvsaj6t",
                "imageUrl": "https://res.cloudinary.com/trackstack/image/upload/v1683127549/arcane_tcxxjq.jpg",
                "imageKey": null,
                "name": "Arcane",
                "slug": "arcane",
                "type": "LABEL",
                "averageReviewTime": 1
            },
            {
                "id": "clgpjrn6b11350jmornk16gjh",
                "imageUrl": "https://res.cloudinary.com/trackstack/image/upload/v1681846585/image_6483441_xkfpvn.jpg",
                "imageKey": null,
                "name": "Spinning Beats",
                "slug": "spinningbeats",
                "type": "LABEL",
                "averageReviewTime": 7
            },
            {
                "id": "clfwi4nbr01790kl2g6umm1sa",
                "imageUrl": "https://res.cloudinary.com/trackstack/image/upload/v1681728319/clip_cyzsfb.jpg",
                "imageKey": null,
                "name": "clipp.art",
                "slug": "clippart",
                "type": "LABEL",
                "averageReviewTime": 1
            },
            {
                "id": "cleiqpusn00730mlb23y8uj2a",
                "imageUrl": null,
                "imageKey": "images/_ceq6s47k3_cimvy2fi-n.png",
                "name": "Music Related Records",
                "slug": "musicrelateddemos",
                "type": "LABEL",
                "averageReviewTime": 1
            },
            {
                "id": "cld8xlnyq00240nkyb29v2lyl",
                "imageUrl": null,
                "imageKey": "images/ax8pp1aglv8noz32tebmt.png",
                "name": "Arms and Legs",
                "slug": "armsandlegs",
                "type": "LABEL",
                "averageReviewTime": 21
            },
            {
                "id": "clfi7ijxg19620ll6bq0dte6c",
                "imageUrl": "https://res.cloudinary.com/trackstack/image/upload/v1679400058/SOT_full_Logo_ladjhc.jpg",
                "imageKey": null,
                "name": "Sands of Time Records",
                "slug": "sandsoftime",
                "type": "LABEL",
                "averageReviewTime": 1
            },
            {
                "id": "cld4ee8ma00870kmjvyh2atlj",
                "imageUrl": "https://res.cloudinary.com/trackstack/image/upload/v1674211524/south_mcktwm.jpg",
                "imageKey": null,
                "name": "South Records",
                "slug": "southrecords",
                "type": "LABEL",
                "averageReviewTime": 7
            },
            {
                "id": "cldismzeu00210kjolmjstq2r",
                "imageUrl": "https://res.cloudinary.com/trackstack/image/upload/v1675021225/uncut_logo_mtpkmw.jpg",
                "imageKey": "images%2F14QkbRkIEVFrVPaL-Pg3L%2Funcut%20logo.jpg",
                "name": "Uncut",
                "slug": "uncut",
                "type": "LABEL",
                "averageReviewTime": 9
            },
            {
                "id": "clgrvwi9a02840kihkks1p12p",
                "imageUrl": "https://res.cloudinary.com/trackstack/image/upload/v1682162093/Bewild_Records_Logo_2023_3000_x_3000_aoolfu.png",
                "imageKey": null,
                "name": "Bewild Records",
                "slug": "bewildrecords",
                "type": "LABEL",
                "averageReviewTime": 7
            },
            {
                "id": "clfqnu4us07930lm9en6zm8eo",
                "imageUrl": "https://res.cloudinary.com/trackstack/image/upload/v1679493808/Blou_Logo_dopufo.png",
                "imageKey": null,
                "name": "Blou Records",
                "slug": "blourecords",
                "type": "LABEL",
                "averageReviewTime": 7
            },
            {
                "id": "clfwi3grr00580jmg88d9um7p",
                "imageUrl": "https://res.cloudinary.com/trackstack/image/upload/v1681728123/You-Do-You-Logo_wi4bjm.jpg",
                "imageKey": null,
                "name": "You Do You",
                "slug": "youdoyou",
                "type": "LABEL",
                "averageReviewTime": 1
            },
            {
                "id": "clagkg6hb0025ms0n6ynhdam5",
                "imageUrl": null,
                "imageKey": null,
                "name": "LoveJuice Recs",
                "slug": "lovejuice",
                "type": "LABEL",
                "averageReviewTime": 7
            },
            {
                "id": "clg104y4g01360kjjbd0wtvvc",
                "imageUrl": "https://res.cloudinary.com/trackstack/image/upload/v1680536673/Profile_Logo_u3m9u1.jpg",
                "imageKey": null,
                "name": "DIRTY HUMANS",
                "slug": "dirtyhumans",
                "type": "LABEL",
                "averageReviewTime": 8
            },
            {
                "id": "clesdf59900070ml70jm870xo",
                "imageUrl": null,
                "imageKey": "images/oxbqy8sgls23rabaoskgd.png",
                "name": "GO WITH THE FLO Records",
                "slug": "gowiththeflo",
                "type": "LABEL",
                "averageReviewTime": 32
            },
            {
                "id": "clfwi1dbp00270kmge9jvhe7c",
                "imageUrl": "https://res.cloudinary.com/trackstack/image/upload/v1681728466/Untitled_design_7_kdvibl.png",
                "imageKey": null,
                "name": "ONELOVE",
                "slug": "onelove",
                "type": "LABEL",
                "averageReviewTime": 8
            },
            {
                "id": "clg2cdny501230lmhr08umvdn",
                "imageUrl": "https://res.cloudinary.com/trackstack/image/upload/v1680617514/appo_hrda85.jpg",
                "imageKey": null,
                "name": "Appolo Records",
                "slug": "appolorecords",
                "type": "LABEL",
                "averageReviewTime": 1
            },
            {
                "id": "clg4zvnw600230ll6wnb686x3",
                "imageUrl": "https://res.cloudinary.com/trackstack/image/upload/v1683131553/alllll_duz02p.jpg",
                "imageKey": "",
                "name": "All We Have Is Now",
                "slug": "allwehaveisnow",
                "type": "LABEL",
                "averageReviewTime": 7
            },
            {
                "id": "clh6eb25f06370jl4iv6rhj1p",
                "imageUrl": null,
                "imageKey": "images/eieyq2cjmscoa60moj0fx.png",
                "name": "DanceOnArrival",
                "slug": "danceonarrival",
                "type": "LABEL",
                "averageReviewTime": 1
            },
            {
                "id": "cl3238z23000109minqt4dmh4",
                "imageUrl": "",
                "imageKey": "images/ngwhffuknhl5z6f-fstwb.png",
                "name": "Electric Party People",
                "slug": "electricpartypeople",
                "type": "LABEL",
                "averageReviewTime": 35
            },
            {
                "id": "cl81df391018909mgm4ts8zla",
                "imageUrl": "https://res.cloudinary.com/trackstack/image/upload/v1663144722/WhatsApp_Image_2022-09-14_at_9.13.26_AM_1_q8kl5y.jpg",
                "imageKey": null,
                "name": "Zest Records",
                "slug": "zest-records",
                "type": "LABEL",
                "averageReviewTime": 30
            },
            {
                "id": "clg7tqk9m01110kl7lal9nvq9",
                "imageUrl": "https://res.cloudinary.com/trackstack/image/upload/v1680948909/naturerec_krseqz.jpg",
                "imageKey": null,
                "name": "Nature Recordings",
                "slug": "naturercd",
                "type": "LABEL",
                "averageReviewTime": 7
            },
            {
                "id": "clgqk3h4r00110jjs021m67ev",
                "imageUrl": "https://res.cloudinary.com/trackstack/image/upload/v1682081559/lovejuice_oku7ml.jpg",
                "imageKey": null,
                "name": "LoveJuice",
                "slug": "wearelovejuice",
                "type": "LABEL",
                "averageReviewTime": 1
            },
            {
                "id": "clgrvt4pg01400kihz7sthzn4",
                "imageUrl": null,
                "imageKey": "images/xry-co34x2zzbwh47cwzi.png",
                "name": "Serpentale Records",
                "slug": "serpentalerecords",
                "type": "LABEL",
                "averageReviewTime": 7
            },
            {
                "id": "clh0bsuel00300mlcxjtbl4xd",
                "imageUrl": null,
                "imageKey": "images/amtr2cknnkssms_tlrko1.png",
                "name": "Creepy Label",
                "slug": "creepylabel",
                "type": "LABEL",
                "averageReviewTime": 7
            },
            {
                "id": "clfgzjdmr00300lmnf4t4u91f",
                "imageUrl": "https://res.cloudinary.com/trackstack/image/upload/v1679326007/Untitled_design_6_dugju2.png",
                "imageKey": null,
                "name": "Mansion Records",
                "slug": "mansionrecords ",
                "type": "LABEL",
                "averageReviewTime": 7
            },
            {
                "id": "clg6klzda01950nmhmtny0jfg",
                "imageUrl": null,
                "imageKey": "images/xekyecgjpdcemoxlehf2w.png",
                "name": "Taturana Records",
                "slug": "taturanarecords",
                "type": "LABEL",
                "averageReviewTime": 7
            },
            {
                "id": "clgchky8z00890nmkph99b15c",
                "imageUrl": "https://res.cloudinary.com/trackstack/image/upload/v1681230849/parallax_symbol-10_zmqcay.jpg",
                "imageKey": null,
                "name": "Parallax",
                "slug": "parallax",
                "type": "LABEL",
                "averageReviewTime": 7
            },
            {
                "id": "clgqmu9r400520jml540pfu9z",
                "imageUrl": "https://res.cloudinary.com/trackstack/image/upload/v1682086457/KiaP9vug_omahjk.jpg",
                "imageKey": null,
                "name": "Kazukuta Records",
                "slug": "kazukutarecords",
                "type": "LABEL",
                "averageReviewTime": 7
            },
            {
                "id": "cld4em16p01820klak23tfv0h",
                "imageUrl": "https://res.cloudinary.com/trackstack/image/upload/v1674211631/Appetite_Logo_Final_Colour_1_-PhotoRoom.png-PhotoRoom_pknaqf.png",
                "imageKey": null,
                "name": "Appetite Records",
                "slug": "appetiterecords",
                "type": "LABEL",
                "averageReviewTime": 7
            },
            {
                "id": "cley5c86509990kl699sqdr19",
                "imageUrl": null,
                "imageKey": "images/wsqzz3kv0a2fl38sxynum.png",
                "name": "Sub_Urban Music",
                "slug": "sub_urban_music",
                "type": "LABEL",
                "averageReviewTime": 7
            },
            {
                "id": "clfy75fks01850li881d3ms0t",
                "imageUrl": null,
                "imageKey": "images/gx4c5m_6tsni2evcdu4vf.png",
                "name": "Superstore Records",
                "slug": "superstorerecords",
                "type": "LABEL",
                "averageReviewTime": 1
            },
            {
                "id": "clgpk88fr06890lmfz8nsu2fx",
                "imageUrl": "https://res.cloudinary.com/trackstack/image/upload/v1682021614/tusk_ipfrq7.jpg",
                "imageKey": null,
                "name": "Tuskegee Music",
                "slug": "tuskegeemusic",
                "type": "LABEL",
                "averageReviewTime": 7
            },
            {
                "id": "clgv72cp704520jlbtjmd7z6o",
                "imageUrl": null,
                "imageKey": "images/txkcagp_oga63qfgm6zxs.png",
                "name": "Fibre Records",
                "slug": "fibrerecords",
                "type": "LABEL",
                "averageReviewTime": 7
            },
            {
                "id": "clgyzafsz00450jmidhwd6e6v",
                "imageUrl": "https://res.cloudinary.com/trackstack/image/upload/v1682591125/adrianza_fezl8w.jpg",
                "imageKey": null,
                "name": "Adrianza Records",
                "slug": "adrianzarecords",
                "type": "LABEL",
                "averageReviewTime": 7
            },
            {
                "id": "cl26byi7c00100wjyk0kauwfz",
                "imageUrl": "",
                "imageKey": null,
                "name": "WDT Records",
                "slug": "wdt-records-xSu-v6dQCQ1IXK5qce6Qp",
                "type": "LABEL",
                "averageReviewTime": 0
            },
            {
                "id": "clex9rsqr00840nme813g613i",
                "imageUrl": "https://res.cloudinary.com/trackstack/image/upload/v1678134122/20687236_2111611799066328_3762737405400973312_a_utceit.jpg",
                "imageKey": null,
                "name": "Fly Boy",
                "slug": "weareflyboy",
                "type": "LABEL",
                "averageReviewTime": 7
            },
            {
                "id": "clfin8fsk01560kll8oc39zta",
                "imageUrl": "https://res.cloudinary.com/trackstack/image/upload/v1679426608/image001_1_ighxt7.png",
                "imageKey": null,
                "name": "DWRTW Records",
                "slug": "dwrtwrecords",
                "type": "LABEL",
                "averageReviewTime": 1
            },
            {
                "id": "clgwe56iq02390ll3roefx244",
                "imageUrl": "https://res.cloudinary.com/trackstack/image/upload/v1682434600/xxlab_hrzamf.jpg",
                "imageKey": null,
                "name": "XX LAB",
                "slug": "xxlab",
                "type": "LABEL",
                "averageReviewTime": 1
            },
            {
                "id": "clgyjf2k501280jjnjoawofqz",
                "imageUrl": null,
                "imageKey": "images/alzhhkknwcjdx7tp1ekfs.png",
                "name": "DIG",
                "slug": "diglabel",
                "type": "LABEL",
                "averageReviewTime": 1
            },
            {
                "id": "clgyzim1r10200kl8107aawwx",
                "imageUrl": "https://res.cloudinary.com/trackstack/image/upload/v1682591477/true_underground_j1jh2v.jpg",
                "imageKey": "images/kakljwdehc8mkhsskcwts.png",
                "name": "Belters @ True Underground",
                "slug": "trueunderground",
                "type": "LABEL",
                "averageReviewTime": 7
            },
            {
                "id": "clh5924ha00600kmb0emwhd8n",
                "imageUrl": null,
                "imageKey": "images/b1snxdee5edjjvyap_vaj.png",
                "name": "Woodlands Records",
                "slug": "woodlandsrecords",
                "type": "LABEL",
                "averageReviewTime": 1
            },
            {
                "id": "clh9j6kkn01910jl3cc1uljta",
                "imageUrl": null,
                "imageKey": "images/qg6msxk7d5xsw8y-dfpow.png",
                "name": "Yolo",
                "slug": "yolo",
                "type": "LABEL",
                "averageReviewTime": 7
            },
            {
                "id": "clhivxro304280kjwqj2opoym",
                "imageUrl": null,
                "imageKey": null,
                "name": "Frontleft",
                "slug": "frontleftmusic",
                "type": "LABEL",
                "averageReviewTime": 7
            },
            {
                "id": "clfgzg18h01320nl8qzbcydwv",
                "imageUrl": "https://res.cloudinary.com/trackstack/image/upload/v1679325998/papa_aqghxc.jpg",
                "imageKey": null,
                "name": "Papa Black Records",
                "slug": "papablackrecords",
                "type": "LABEL",
                "averageReviewTime": 1
            },
            {
                "id": "clgqfe8rv03410jjrs3hw23xv",
                "imageUrl": "https://res.cloudinary.com/trackstack/image/upload/v1682081304/ooo_umvjqu.jpg",
                "imageKey": null,
                "name": "Out Of Options",
                "slug": "outofoptions",
                "type": "LABEL",
                "averageReviewTime": 1
            },
            {
                "id": "clgqmdqsm00180jmkfcvb21ht",
                "imageUrl": "https://res.cloudinary.com/trackstack/image/upload/v1682085458/Image-1_1_1_ao1ltz.jpg",
                "imageKey": null,
                "name": "TRÈS BIEN",
                "slug": "tresbien",
                "type": "LABEL",
                "averageReviewTime": 1
            },
            {
                "id": "clgw9qej400000kjsfuoceul8",
                "imageUrl": "https://res.cloudinary.com/trackstack/image/upload/v1682427189/Untitled_design_8_etddpv.png",
                "imageKey": null,
                "name": "Buriloop Records",
                "slug": "burilooprecords",
                "type": "LABEL",
                "averageReviewTime": 1
            },
            {
                "id": "clgw9wapm01230kjs1tgsiu19",
                "imageUrl": "https://res.cloudinary.com/trackstack/image/upload/v1682427409/BABUCO_-_1_ctghg7.png",
                "imageKey": "images/qeggg9ej8ddghegmxtpwk.png",
                "name": "XAMXARA",
                "slug": "xamxara",
                "type": "LABEL",
                "averageReviewTime": 1
            },
            {
                "id": "clh0hv7da02750kjrv1kjy8h7",
                "imageUrl": null,
                "imageKey": "images/3ez6ceg6prdmremqhoya7.png",
                "name": "Bukkle Records",
                "slug": "bukklerecords",
                "type": "LABEL",
                "averageReviewTime": 1
            },
            {
                "id": "clhajayb310940jkwp5q5jz2y",
                "imageUrl": "https://res.cloudinary.com/trackstack/image/upload/v1683289656/ATM_1_tnvgo6.jpg",
                "imageKey": null,
                "name": "Atmosphere Records",
                "slug": "atmosphererecords",
                "type": "LABEL",
                "averageReviewTime": 1
            },
            {
                "id": "clhajbk3h11320jkwq45sqvki",
                "imageUrl": "https://res.cloudinary.com/trackstack/image/upload/v1683289964/Untitled_design_10_wgax8f.png",
                "imageKey": null,
                "name": "Ontourage Music",
                "slug": "ontouragemusic",
                "type": "LABEL",
                "averageReviewTime": 1
            }
        ]
    }
}